{"cameraMode":{"drawMode":0,"name":"Shaded","section":"Shading Mode"},"sceneLighting":false,"audioPlay":false,"sceneViewState":{"showFog":true,"showMaterialUpdate":false,"showSkybox":false,"showFlares":true,"showImageEffects":true,"showParticleSystems":true},"in2DMode":false,"pivot":{"x":-3.207512855529785,"y":2.4672837257385256,"z":0.5655721426010132},"rotation":{"x":0.04217865318059921,"y":0.7910695672035217,"z":-0.05493113398551941,"w":0.6078607439994812},"size":2.171992778778076,"orthographic":false}